{
  "last_updated": "2026-02-19T06:56:42.712249",
  "source": "iNaturalist",
  "taxon_id": "551307",
  "count": 30,
  "observations": [
    {
      "id": 339206335,
      "image_url": "https://inaturalist-open-data.s3.amazonaws.com/photos/617008594/large.gif",
      "species_common": "Common Smooth-hound",
      "species_scientific": "Mustelus mustelus",
      "observer": "N\u00e9stor Negr\u00edn Arteaga",
      "observer_login": "nestork66",
      "date": "2026/02/08",
      "location": "Location obscured",
      "license_code": "cc-by-nc-nd",
      "license_name": "CC BY-NC-ND",
      "license_url": "https://creativecommons.org/licenses/by-nc-nd/4.0/",
      "obs_url": "https://www.inaturalist.org/observations/339206335",
      "quality_grade": "research"
    },
    {
      "id": 339061686,
      "image_url": "https://inaturalist-open-data.s3.amazonaws.com/photos/616713823/large.jpg",
      "species_common": "Great White Shark",
      "species_scientific": "Carcharodon carcharias",
      "observer": "charlie",
      "observer_login": "cclayton414",
      "date": "2026-02-07 08:30:46",
      "location": "Western Cape, ZA",
      "license_code": "cc-by-nc",
      "license_name": "CC BY-NC",
      "license_url": "https://creativecommons.org/licenses/by-nc/4.0/",
      "obs_url": "https://www.inaturalist.org/observations/339061686",
      "quality_grade": "research"
    },
    {
      "id": 339039041,
      "image_url": "https://inaturalist-open-data.s3.amazonaws.com/photos/616667736/large.jpg",
      "species_common": "Puffadder Shyshark",
      "species_scientific": "Haploblepharus edwardsii",
      "observer": "Ruth Rudolph",
      "observer_login": "ruths_adventures",
      "date": "2026-02-17",
      "location": "Western Cape, ZA",
      "license_code": "cc-by-nc",
      "license_name": "CC BY-NC",
      "license_url": "https://creativecommons.org/licenses/by-nc/4.0/",
      "obs_url": "https://www.inaturalist.org/observations/339039041",
      "quality_grade": "research"
    },
    {
      "id": 339032460,
      "image_url": "https://inaturalist-open-data.s3.amazonaws.com/photos/616655146/large.jpg",
      "species_common": "Whitetip Reef Shark",
      "species_scientific": "Triaenodon obesus",
      "observer": null,
      "observer_login": "alwaysshootfirst",
      "date": "2026-02-17 21:27:52+07:00",
      "location": "\u5b89\u8fbe\u66fc\u6d77, TH",
      "license_code": "cc-by-nc",
      "license_name": "CC BY-NC",
      "license_url": "https://creativecommons.org/licenses/by-nc/4.0/",
      "obs_url": "https://www.inaturalist.org/observations/339032460",
      "quality_grade": "research"
    },
    {
      "id": 339009107,
      "image_url": "https://inaturalist-open-data.s3.amazonaws.com/photos/616603330/large.jpg",
      "species_common": "Puffadder Shyshark",
      "species_scientific": "Haploblepharus edwardsii",
      "observer": "Di Boonman",
      "observer_login": "diederik_7",
      "date": "2026/02/16 2:05 PM",
      "location": "Western Cape, ZA",
      "license_code": "cc-by-nc",
      "license_name": "CC BY-NC",
      "license_url": "https://creativecommons.org/licenses/by-nc/4.0/",
      "obs_url": "https://www.inaturalist.org/observations/339009107",
      "quality_grade": "research"
    },
    {
      "id": 338948777,
      "image_url": "https://inaturalist-open-data.s3.amazonaws.com/photos/616487207/large.jpg",
      "species_common": "Crested Hornshark",
      "species_scientific": "Heterodontus galeatus",
      "observer": "Lynne",
      "observer_login": "scubalynne",
      "date": "2026/02/16 7:45 AM",
      "location": "Sydney NSW, Australia",
      "license_code": "cc-by-nc",
      "license_name": "CC BY-NC",
      "license_url": "https://creativecommons.org/licenses/by-nc/4.0/",
      "obs_url": "https://www.inaturalist.org/observations/338948777",
      "quality_grade": "research"
    },
    {
      "id": 338945250,
      "image_url": "https://inaturalist-open-data.s3.amazonaws.com/photos/616481337/large.jpg",
      "species_common": "Typical Requiem Sharks",
      "species_scientific": "Carcharhinus",
      "observer": "Kristina Weis",
      "observer_login": "kristinaweis",
      "date": "2017/03/23 10:49 AM",
      "location": "Florida Keys National Marine Sanctuary, FL, USA",
      "license_code": "cc-by-nc",
      "license_name": "CC BY-NC",
      "license_url": "https://creativecommons.org/licenses/by-nc/4.0/",
      "obs_url": "https://www.inaturalist.org/observations/338945250",
      "quality_grade": "needs_id"
    },
    {
      "id": 338913629,
      "image_url": "https://inaturalist-open-data.s3.amazonaws.com/photos/616420936/large.jpg",
      "species_common": "Common Blacktip Shark",
      "species_scientific": "Carcharhinus limbatus",
      "observer": "Mae Mayville",
      "observer_login": "maemay",
      "date": "2026-02-16 11:51:54",
      "location": "Florida, US",
      "license_code": "cc-by-nc",
      "license_name": "CC BY-NC",
      "license_url": "https://creativecommons.org/licenses/by-nc/4.0/",
      "obs_url": "https://www.inaturalist.org/observations/338913629",
      "quality_grade": "research"
    },
    {
      "id": 338855701,
      "image_url": "https://inaturalist-open-data.s3.amazonaws.com/photos/616312507/large.jpg",
      "species_common": "Ornate Wobbegong",
      "species_scientific": "Orectolobus ornatus",
      "observer": "",
      "observer_login": "mattdowse",
      "date": "2026/02/16 7:33 AM",
      "location": "Nelson Bay NSW 2315, Australia",
      "license_code": "cc-by-nc",
      "license_name": "CC BY-NC",
      "license_url": "https://creativecommons.org/licenses/by-nc/4.0/",
      "obs_url": "https://www.inaturalist.org/observations/338855701",
      "quality_grade": "research"
    },
    {
      "id": 338842068,
      "image_url": "https://inaturalist-open-data.s3.amazonaws.com/photos/616285696/large.jpg",
      "species_common": "Whitetip Reef Shark",
      "species_scientific": "Triaenodon obesus",
      "observer": "",
      "observer_login": "wsyxbcl",
      "date": "2026-02-12",
      "location": "\u83f2\u5f8b\u5bbe\u4fdd\u548c\u90a6\u52b3GM8J+QRJ",
      "license_code": "cc-by-nc",
      "license_name": "CC BY-NC",
      "license_url": "https://creativecommons.org/licenses/by-nc/4.0/",
      "obs_url": "https://www.inaturalist.org/observations/338842068",
      "quality_grade": "research"
    },
    {
      "id": 338754136,
      "image_url": "https://inaturalist-open-data.s3.amazonaws.com/photos/616104833/large.jpg",
      "species_common": "Blacktip Reef Shark",
      "species_scientific": "Carcharhinus melanopterus",
      "observer": "Frank Krasovec",
      "observer_login": "wetlens",
      "date": "2014/11/01 3:37 PM",
      "location": "Solomon Islands",
      "license_code": "cc-by-nc",
      "license_name": "CC BY-NC",
      "license_url": "https://creativecommons.org/licenses/by-nc/4.0/",
      "obs_url": "https://www.inaturalist.org/observations/338754136",
      "quality_grade": "research"
    },
    {
      "id": 338683783,
      "image_url": "https://inaturalist-open-data.s3.amazonaws.com/photos/615966243/large.jpg",
      "species_common": "Cobbler Wobbegong",
      "species_scientific": "Sutorectus tentaculatus",
      "observer": "murron handley",
      "observer_login": "murron203",
      "date": "2026/02/14 2:18 PM",
      "location": "Woodman point, Coogee WA 6166, Australia",
      "license_code": "cc-by-nc",
      "license_name": "CC BY-NC",
      "license_url": "https://creativecommons.org/licenses/by-nc/4.0/",
      "obs_url": "https://www.inaturalist.org/observations/338683783",
      "quality_grade": "research"
    },
    {
      "id": 338546061,
      "image_url": "https://inaturalist-open-data.s3.amazonaws.com/photos/615700625/large.jpg",
      "species_common": "Bull Shark",
      "species_scientific": "Carcharhinus leucas",
      "observer": "Hamish Baxter-Curtis",
      "observer_login": "hamish26345",
      "date": "2026-02-14 19:35:12",
      "location": "Riverview QLD 4303, Australia",
      "license_code": "cc-by-nc",
      "license_name": "CC BY-NC",
      "license_url": "https://creativecommons.org/licenses/by-nc/4.0/",
      "obs_url": "https://www.inaturalist.org/observations/338546061",
      "quality_grade": "research"
    },
    {
      "id": 338471529,
      "image_url": "https://inaturalist-open-data.s3.amazonaws.com/photos/615543955/large.jpg",
      "species_common": "Nurse Shark",
      "species_scientific": "Ginglymostoma cirratum",
      "observer": "Frank Krasovec",
      "observer_login": "wetlens",
      "date": "2014/12/10 11:51 AM",
      "location": "Kralendijk, Caribbean Netherlands",
      "license_code": "cc-by-nc",
      "license_name": "CC BY-NC",
      "license_url": "https://creativecommons.org/licenses/by-nc/4.0/",
      "obs_url": "https://www.inaturalist.org/observations/338471529",
      "quality_grade": "research"
    },
    {
      "id": 338444207,
      "image_url": "https://inaturalist-open-data.s3.amazonaws.com/photos/615490047/large.jpg",
      "species_common": "Common Blacktip Shark",
      "species_scientific": "Carcharhinus limbatus",
      "observer": "Lucas Scott de Marcos",
      "observer_login": "koala_sprint",
      "date": "2026-02-12 18:55:32",
      "location": "Santa Cruz, EC-GA, EC",
      "license_code": "cc-by-nc",
      "license_name": "CC BY-NC",
      "license_url": "https://creativecommons.org/licenses/by-nc/4.0/",
      "obs_url": "https://www.inaturalist.org/observations/338444207",
      "quality_grade": "research"
    },
    {
      "id": 338444059,
      "image_url": "https://inaturalist-open-data.s3.amazonaws.com/photos/615489867/large.jpg",
      "species_common": "Common Blacktip Shark",
      "species_scientific": "Carcharhinus limbatus",
      "observer": "Lucas Scott de Marcos",
      "observer_login": "koala_sprint",
      "date": "2026-02-12 11:42:41",
      "location": "Santa Cruz, EC-GA, EC",
      "license_code": "cc-by-nc",
      "license_name": "CC BY-NC",
      "license_url": "https://creativecommons.org/licenses/by-nc/4.0/",
      "obs_url": "https://www.inaturalist.org/observations/338444059",
      "quality_grade": "research"
    },
    {
      "id": 338352967,
      "image_url": "https://inaturalist-open-data.s3.amazonaws.com/photos/615297018/large.jpg",
      "species_common": "Whale Shark",
      "species_scientific": "Rhincodon typus",
      "observer": "Frank Krasovec",
      "observer_login": "wetlens",
      "date": "2015/10/31 9:02 AM",
      "location": "Philippines",
      "license_code": "cc-by-nc",
      "license_name": "CC BY-NC",
      "license_url": "https://creativecommons.org/licenses/by-nc/4.0/",
      "obs_url": "https://www.inaturalist.org/observations/338352967",
      "quality_grade": "research"
    },
    {
      "id": 338269077,
      "image_url": "https://inaturalist-open-data.s3.amazonaws.com/photos/615123424/large.jpg",
      "species_common": "Spotted Houndshark",
      "species_scientific": "Triakis maculata",
      "observer": "Aroon Estrada",
      "observer_login": "aroonwt",
      "date": "2026-02-11",
      "location": "Lima, PE-LP, PE",
      "license_code": "cc-by-nc",
      "license_name": "CC BY-NC",
      "license_url": "https://creativecommons.org/licenses/by-nc/4.0/",
      "obs_url": "https://www.inaturalist.org/observations/338269077",
      "quality_grade": "research"
    },
    {
      "id": 338214705,
      "image_url": "https://inaturalist-open-data.s3.amazonaws.com/photos/615010492/large.jpg",
      "species_common": "Nurse Shark",
      "species_scientific": "Ginglymostoma cirratum",
      "observer": "Mitch Lindgren",
      "observer_login": "mlindgren",
      "date": "2026-02-11 09:44:25-06:00",
      "location": "Caribbean Sea, Corozal, BZ",
      "license_code": "cc-by-nc",
      "license_name": "CC BY-NC",
      "license_url": "https://creativecommons.org/licenses/by-nc/4.0/",
      "obs_url": "https://www.inaturalist.org/observations/338214705",
      "quality_grade": "research"
    },
    {
      "id": 338181671,
      "image_url": "https://inaturalist-open-data.s3.amazonaws.com/photos/614942901/large.jpg",
      "species_common": "Whitetip Reef Shark",
      "species_scientific": "Triaenodon obesus",
      "observer": "porcoesphino",
      "observer_login": "porcoesphino",
      "date": "2026-02-11 10:00:00+05:00",
      "location": "Indian Ocean, Baa, MV",
      "license_code": "cc-by-nc-nd",
      "license_name": "CC BY-NC-ND",
      "license_url": "https://creativecommons.org/licenses/by-nc-nd/4.0/",
      "obs_url": "https://www.inaturalist.org/observations/338181671",
      "quality_grade": "research"
    },
    {
      "id": 338178766,
      "image_url": "https://inaturalist-open-data.s3.amazonaws.com/photos/614937121/large.jpg",
      "species_common": "Blacktip Reef Shark",
      "species_scientific": "Carcharhinus melanopterus",
      "observer": null,
      "observer_login": "louvanhaeren",
      "date": "2026/02/07 4:25 PM",
      "location": "Raja Ampat, ID-IB, ID",
      "license_code": "cc-by-nc",
      "license_name": "CC BY-NC",
      "license_url": "https://creativecommons.org/licenses/by-nc/4.0/",
      "obs_url": "https://www.inaturalist.org/observations/338178766",
      "quality_grade": "research"
    },
    {
      "id": 338178764,
      "image_url": "https://inaturalist-open-data.s3.amazonaws.com/photos/614937039/large.jpg",
      "species_common": "Tasselled Wobbegong",
      "species_scientific": "Eucrossorhinus dasypogon",
      "observer": null,
      "observer_login": "louvanhaeren",
      "date": "2026/02/07 4:25 PM",
      "location": "Raja Ampat, ID-IB, ID",
      "license_code": "cc-by-nc",
      "license_name": "CC BY-NC",
      "license_url": "https://creativecommons.org/licenses/by-nc/4.0/",
      "obs_url": "https://www.inaturalist.org/observations/338178764",
      "quality_grade": "research"
    },
    {
      "id": 338178762,
      "image_url": "https://inaturalist-open-data.s3.amazonaws.com/photos/614936964/large.jpg",
      "species_common": "Tasselled Wobbegong",
      "species_scientific": "Eucrossorhinus dasypogon",
      "observer": null,
      "observer_login": "louvanhaeren",
      "date": "2026/02/07 4:25 PM",
      "location": "Raja Ampat, ID-IB, ID",
      "license_code": "cc-by-nc",
      "license_name": "CC BY-NC",
      "license_url": "https://creativecommons.org/licenses/by-nc/4.0/",
      "obs_url": "https://www.inaturalist.org/observations/338178762",
      "quality_grade": "research"
    },
    {
      "id": 338171222,
      "image_url": "https://inaturalist-open-data.s3.amazonaws.com/photos/614923346/large.jpg",
      "species_common": "Epaulette Shark",
      "species_scientific": "Hemiscyllium ocellatum",
      "observer": "Ocean Safari",
      "observer_login": "ocean_safari",
      "date": "2026/02/11 4:28 PM",
      "location": "Location obscured",
      "license_code": "cc-by-nc",
      "license_name": "CC BY-NC",
      "license_url": "https://creativecommons.org/licenses/by-nc/4.0/",
      "obs_url": "https://www.inaturalist.org/observations/338171222",
      "quality_grade": "research"
    },
    {
      "id": 338115914,
      "image_url": "https://inaturalist-open-data.s3.amazonaws.com/photos/614809071/large.jpg",
      "species_common": "Zebra Shark",
      "species_scientific": "Stegostoma tigrinum",
      "observer": null,
      "observer_login": "tantleo",
      "date": "2025-06-16 09:02:15",
      "location": "AU",
      "license_code": "cc-by-nc",
      "license_name": "CC BY-NC",
      "license_url": "https://creativecommons.org/licenses/by-nc/4.0/",
      "obs_url": "https://www.inaturalist.org/observations/338115914",
      "quality_grade": "research"
    },
    {
      "id": 338014043,
      "image_url": "https://inaturalist-open-data.s3.amazonaws.com/photos/614590288/large.jpg",
      "species_common": "Whitetip Reef Shark",
      "species_scientific": "Triaenodon obesus",
      "observer": null,
      "observer_login": "vivekaocherik",
      "date": "2026/01/26 12:55",
      "location": "Montijo District, Veraguas Province, Panama",
      "license_code": "cc-by-nc",
      "license_name": "CC BY-NC",
      "license_url": "https://creativecommons.org/licenses/by-nc/4.0/",
      "obs_url": "https://www.inaturalist.org/observations/338014043",
      "quality_grade": "research"
    },
    {
      "id": 337934760,
      "image_url": "https://inaturalist-open-data.s3.amazonaws.com/photos/614439054/large.jpg",
      "species_common": "Zebra Shark",
      "species_scientific": "Stegostoma tigrinum",
      "observer": "Keith Morris",
      "observer_login": "boobook99",
      "date": "2013/02/26 9:51 AM",
      "location": "Palau",
      "license_code": "cc-by-nc",
      "license_name": "CC BY-NC",
      "license_url": "https://creativecommons.org/licenses/by-nc/4.0/",
      "obs_url": "https://www.inaturalist.org/observations/337934760",
      "quality_grade": "research"
    },
    {
      "id": 337877390,
      "image_url": "https://inaturalist-open-data.s3.amazonaws.com/photos/614319730/large.jpg",
      "species_common": "Tiger Shark",
      "species_scientific": "Galeocerdo cuvier",
      "observer": "Robin",
      "observer_login": "ropps",
      "date": "2026-02-08 09:03:39",
      "location": "\u00celes Tuamotu-Gambier, PF",
      "license_code": "cc-by-nc-nd",
      "license_name": "CC BY-NC-ND",
      "license_url": "https://creativecommons.org/licenses/by-nc-nd/4.0/",
      "obs_url": "https://www.inaturalist.org/observations/337877390",
      "quality_grade": "research"
    },
    {
      "id": 337877176,
      "image_url": "https://inaturalist-open-data.s3.amazonaws.com/photos/614319234/large.jpg",
      "species_common": "Port Jackson Shark",
      "species_scientific": "Heterodontus portusjacksoni",
      "observer": null,
      "observer_login": "clawhammer-andy",
      "date": "2026-02-09 10:07:04",
      "location": "Foreshore Rd, Hardwicke Bay, SA, AU",
      "license_code": "cc-by-nc",
      "license_name": "CC BY-NC",
      "license_url": "https://creativecommons.org/licenses/by-nc/4.0/",
      "obs_url": "https://www.inaturalist.org/observations/337877176",
      "quality_grade": "research"
    },
    {
      "id": 337865236,
      "image_url": "https://inaturalist-open-data.s3.amazonaws.com/photos/614294949/large.jpg",
      "species_common": "Small-spotted Catshark",
      "species_scientific": "Scyliorhinus canicula",
      "observer": null,
      "observer_login": "uxbridgebirder",
      "date": "2026-02-08 16:36:23",
      "location": "Romney Marsh, England, GB",
      "license_code": "cc-by",
      "license_name": "CC BY",
      "license_url": "https://creativecommons.org/licenses/by/4.0/",
      "obs_url": "https://www.inaturalist.org/observations/337865236",
      "quality_grade": "research"
    }
  ]
}